[
  {
    "email": "ebernal@bwl.com.mx",
    "enabled": true,
    "force2FA": false,
    "hash": "$2a$10$/uV2I8UIbi4TR4BqakmJLugI7vocj0dyZE2NElOz9U67c3d28BnoW",
    "hash2FA": "",
    "lastJwt": "",
    "lastPasswordChange": "2023-11-16 17:10:50.941000",
    "name": "Eli Bernal",
    "preAuth": null,
    "superUser": false,
    "twoFactorAuth": false,
    "twoFactorAuthLimit": null,
    "username": "ebernal",
    "lastLoginTime": null,
    "recoveryToken": null,
    "credentialsExpired": false,
    "creationDate": "2023-11-16 17:10:50.941000"
  },
  {
    "email": "wbernal@bwl.com.mx",
    "enabled": true,
    "force2FA": false,
    "hash": "$2a$10$/uV2I8UIbi4TR4BqakmJLugI7vocj0dyZE2NElOz9U67c3d28BnoW",
    "hash2FA": "",
    "lastJwt": "",
    "lastPasswordChange": "2023-11-17 16:45:05.091000",
    "name": "Walter Bernal",
    "preAuth": null,
    "superUser": false,
    "twoFactorAuth": false,
    "twoFactorAuthLimit": null,
    "username": "wbernal",
    "lastLoginTime": null,
    "recoveryToken": null,
    "credentialsExpired": false,
    "creationDate": "2023-11-17 16:45:05.091000"
  },
  {
    "email": "emontero@bwl.com.mx",
    "enabled": true,
    "force2FA": false,
    "hash": "$2a$10$/uV2I8UIbi4TR4BqakmJLugI7vocj0dyZE2NElOz9U67c3d28BnoW",
    "hash2FA": "",
    "lastJwt": "",
    "lastPasswordChange": "2023-11-21 22:54:02.481000",
    "name": "John Spartan",
    "preAuth": null,
    "superUser": false,
    "twoFactorAuth": false,
    "twoFactorAuthLimit": null,
    "username": "john117",
    "lastLoginTime": null,
    "recoveryToken": null,
    "credentialsExpired": false,
    "creationDate": "2023-11-21 22:54:02.481000"
  }
]